Metadata-Version: 2.1
Name: CustomCFLib
Version: 1.0
Summary: Za potrebe ARIS-a
Home-page: https://github.com/matijavugrinec/CustomCFLib/
Download-URL: https://github.com/matijavugrinec/CustomCFLib/archive/refs/tags/v_10.tar.gz
Author: Matija VUgrinec
Author-email: matija.vugrinec0@gmail.com
License: MIT
Keywords: CF,ARIS,HARDWORK
Classifier: Development Status :: 3 - Alpha
Classifier: Intended Audience :: Developers
Classifier: Topic :: Software Development :: Build Tools
Classifier: License :: OSI Approved :: MIT License
Classifier: Programming Language :: Python :: 3
Classifier: Programming Language :: Python :: 3.4
Classifier: Programming Language :: Python :: 3.5
Classifier: Programming Language :: Python :: 3.6
License-File: LICENSE.txt
